LICENSE
MANIFEST.in
README.rst
mattersend.py
setup.cfg
setup.py
mattersend.egg-info/PKG-INFO
mattersend.egg-info/SOURCES.txt
mattersend.egg-info/dependency_links.txt
mattersend.egg-info/entry_points.txt
mattersend.egg-info/requires.txt
mattersend.egg-info/top_level.txt