Metadata-Version: 1.1
Name: mattersend
Version: 2.0
Summary: Library and CLI utility to send messages to mattermost's incoming webhooks
Home-page: https://github.com/mtorromeo/mattersend
Author: Massimiliano Torromeo
Author-email: massimiliano.torromeo@gmail.com
License: MIT License
Download-URL: https://github.com/mtorromeo/mattersend/tarball/v2.0
Platform: UNKNOWN
Classifier: Programming Language :: Python
Classifier: Programming Language :: Python :: 3.4
Classifier: License :: OSI Approved :: MIT License
Classifier: Intended Audience :: System Administrators
Classifier: Operating System :: POSIX :: Linux
Classifier: Natural Language :: English
Classifier: Topic :: Utilities
